README.md
setup.py
tests/__init__.py
tests/test_build_runner.py
tests/ml_qookeys/__init__.py
tests/ml_qookeys/src/__init__.py
tests/ml_qookeys/src/data_processing/__init__.py
tests/ml_qookeys/src/data_processing/merge_fit.py
tests/ml_qookeys/src/data_processing/merge_predict.py
tests/ml_qookeys/src/data_processing/process_fit.py
tests/ml_qookeys/src/data_processing/process_predict.py
tests/ml_qookeys/src/feature_engineering/__init__ 2.py
tests/ml_qookeys/src/feature_engineering/__init__.py
tests/ml_qookeys/src/feature_engineering/merge_fit.py
tests/ml_qookeys/src/feature_engineering/merge_predict 2.py
tests/ml_qookeys/src/feature_engineering/merge_predict.py
tests/ml_qookeys/src/feature_engineering/process_1_fit 2.py
tests/ml_qookeys/src/feature_engineering/process_1_fit.py
tests/ml_qookeys/src/feature_engineering/process_1_predict 2.py
tests/ml_qookeys/src/feature_engineering/process_1_predict.py
tests/ml_qookeys/src/feature_engineering/process_2.py
tests/ml_qookeys/src/feature_selection/__init__ 2.py
tests/ml_qookeys/src/feature_selection/__init__.py
tests/ml_qookeys/src/feature_selection/merge.py
tests/ml_qookeys/src/feature_selection/process.py
tests/ml_qookeys/src/model_training/__init__ 2.py
tests/ml_qookeys/src/model_training/__init__.py
tests/ml_qookeys/src/model_training/merge 2.py
tests/ml_qookeys/src/model_training/merge.py
tests/ml_qookeys/src/model_training/model_1 2.py
tests/ml_qookeys/src/model_training/model_1.py
tests/ml_qookeys/src/model_training/model_2 2.py
tests/ml_qookeys/src/model_training/model_2.py
tests/ml_qookeys/src/model_validation/__init__.py
tests/ml_qookeys/src/model_validation/merge.py
tests/ml_qookeys/src/model_validation/validate_1.py
tests/ml_qookeys/src/model_validation/validate_2.py
tests/ml_qookeys/src/serve/__init__.py
tests/ml_qookeys/src/serve/merge.py
tests/ml_qookeys/src/serve/process.py
tests/ml_qookeys/tests/__init__.py
tests/trainingopz/__init__.py
tests/trainingopz/test_director.py
trainingopz.egg-info/PKG-INFO
trainingopz.egg-info/SOURCES.txt
trainingopz.egg-info/dependency_links.txt
trainingopz.egg-info/top_level.txt
