Metadata-Version: 2.1
Name: trainingopz
Version: 0.1.3.43
Summary: DO NOT USE - This is a sample program
Home-page: https://github.com/hashmapinc/trainingopz
Author: Hashmap, Inc
Author-email: accelerators@hashmapinc.com
License: UNKNOWN
Platform: UNKNOWN
Classifier: Programming Language :: Python :: 3
Classifier: License :: OSI Approved :: Apache Software License
Classifier: Operating System :: OS Independent
Classifier: Development Status :: 4 - Beta
Requires-Python: >=3.6
